dh_json_logger-0.1.1.dist-info/licenses/LICENSE
json_logger/__init__.py
json_logger/formatter.py
dh_json_logger-0.1.1.dist-info/METADATA
dh_json_logger-0.1.1.dist-info/WHEEL
dh_json_logger-0.1.1.dist-info/top_level.txt
dh_json_logger-0.1.1.dist-info/RECORD
