Metadata-Version: 2.4
Name: dh-json-logger
Version: 0.1.1
Summary: A robust JSON logging library for Python
Author-email: Dillan Hoyos <dillanhoyosmusic@gmail.com>
Project-URL: Homepage, https://github.com/dillanhoyos/python-JSON-Logger
Project-URL: Bug Tracker, https://github.com/dillanhoyos/python-JSON-Logger/issues
Classifier: Programming Language :: Python :: 3
Classifier: License :: OSI Approved :: MIT License
Classifier: Operating System :: OS Independent
Classifier: Development Status :: 3 - Alpha
Classifier: Intended Audience :: Developers
Classifier: Topic :: System :: Logging
Requires-Python: >=3.7
License-File: LICENSE
Provides-Extra: dev
Requires-Dist: pytest; extra == "dev"
Requires-Dist: flake8; extra == "dev"
Requires-Dist: mypy; extra == "dev"
Requires-Dist: build; extra == "dev"
Requires-Dist: twine; extra == "dev"
Dynamic: license-file
